zhmcclient/__init__.py
zhmcclient/_activation_profile.py
zhmcclient/_adapter.py
zhmcclient/_auto_updater.py
zhmcclient/_capacity_group.py
zhmcclient/_certificates.py
zhmcclient/_client.py
zhmcclient/_console.py
zhmcclient/_constants.py
zhmcclient/_cpc.py
zhmcclient/_debug_info.py
zhmcclient/_exceptions.py
zhmcclient/_group.py
zhmcclient/_hba.py
zhmcclient/_hw_message.py
zhmcclient/_ldap_server_definition.py
zhmcclient/_logging.py
zhmcclient/_lpar.py
zhmcclient/_manager.py
zhmcclient/_metrics.py
zhmcclient/_mfa_server_definition.py
zhmcclient/_nic.py
zhmcclient/_notification.py
zhmcclient/_os_console.py
zhmcclient/_partition.py
zhmcclient/_partition_link.py
zhmcclient/_password_rule.py
zhmcclient/_port.py
zhmcclient/_resource.py
zhmcclient/_session.py
zhmcclient/_storage_group.py
zhmcclient/_storage_group_template.py
zhmcclient/_storage_volume.py
zhmcclient/_storage_volume_template.py
zhmcclient/_task.py
zhmcclient/_timestats.py
zhmcclient/_unmanaged_cpc.py
zhmcclient/_user.py
zhmcclient/_user_pattern.py
zhmcclient/_user_role.py
zhmcclient/_utils.py
zhmcclient/_version.py
zhmcclient/_version_scm.py
zhmcclient/_virtual_function.py
zhmcclient/_virtual_storage_resource.py
zhmcclient/_virtual_switch.py
zhmcclient/_vendor/__init__.py
zhmcclient/_vendor/python/__init__.py
zhmcclient/_vendor/python/ssl.py
zhmcclient/mock/__init__.py
zhmcclient/mock/_hmc.py
zhmcclient/mock/_idpool.py
zhmcclient/mock/_session.py
zhmcclient/mock/_urihandler.py
zhmcclient/testutils/__init__.py
zhmcclient/testutils/_cpc_fixtures.py
zhmcclient/testutils/_hmc_definition.py
zhmcclient/testutils/_hmc_definition_fixtures.py
zhmcclient/testutils/_hmc_definitions.py
zhmcclient/testutils/_hmc_inventory_file.py
zhmcclient/testutils/_hmc_session_functions.py
zhmcclient/testutils/_hmc_vault_file.py
zhmcclient-1.25.0.dist-info/licenses/LICENSE
zhmcclient_mock/__init__.py
zhmcclient-1.25.0.dist-info/METADATA
zhmcclient-1.25.0.dist-info/WHEEL
zhmcclient-1.25.0.dist-info/entry_points.txt
zhmcclient-1.25.0.dist-info/top_level.txt
zhmcclient-1.25.0.dist-info/zip-safe
zhmcclient-1.25.0.dist-info/RECORD
