Metadata-Version: 2.4
Name: zhmcclient
Version: 1.25.0
Summary: A pure Python client library for the IBM Z HMC Web Services API
Author-email: Juergen Leopold <leopoldj@de.ibm.com>, Andreas Maier <maiera@de.ibm.com>
Maintainer-email: Andreas Maier <maiera@de.ibm.com>, Kathir Velusamy <kathir.velu@in.ibm.com'>
License-Expression: Apache-2.0
Project-URL: Homepage, https://github.com/zhmcclient/python-zhmcclient
Project-URL: Bug Tracker, https://github.com/zhmcclient/python-zhmcclient/issues
Project-URL: Documentation, https://python-zhmcclient.readthedocs.io
Project-URL: Source Code, https://github.com/zhmcclient/python-zhmcclient
Project-URL: Changelog, https://python-zhmcclient.readthedocs.io/en/master/changes.html
Keywords: hmc,client
Platform: any
Classifier: Development Status :: 5 - Production/Stable
Classifier: Intended Audience :: Developers
Classifier: Intended Audience :: Information Technology
Classifier: Topic :: Software Development :: Libraries :: Python Modules
Classifier: Topic :: System :: Systems Administration
Classifier: Environment :: Console
Classifier: Operating System :: OS Independent
Classifier: Programming Language :: Python :: 3
Classifier: Programming Language :: Python :: 3.9
Classifier: Programming Language :: Python :: 3.10
Classifier: Programming Language :: Python :: 3.11
Classifier: Programming Language :: Python :: 3.12
Classifier: Programming Language :: Python :: 3.13
Classifier: Programming Language :: Python :: 3.14
Requires-Python: >=3.9
License-File: LICENSE
Requires-Dist: requests>=2.32.4
Requires-Dist: stomp-py>=8.1.1
Requires-Dist: immutabledict>=4.2.0
Requires-Dist: nocasedict>=1.0.2
Requires-Dist: PyYAML>=6.0.2
Requires-Dist: jsonschema>=4.18.0
Requires-Dist: websocket-client>=1.8.0
Requires-Dist: certifi>=2024.07.04
Requires-Dist: urllib3>=2.6.0
Requires-Dist: idna>=3.7
Provides-Extra: testutils
Requires-Dist: pytest>=8.4.0; extra == "testutils"
Dynamic: license-file
